agnpy/__init__.py
agnpy/absorption/__init__.py
agnpy/absorption/absorption.py
agnpy/compton/__init__.py
agnpy/compton/external_compton.py
agnpy/compton/kernels.py
agnpy/compton/synchrotron_self_compton.py
agnpy/constraints/__init__.py
agnpy/constraints/spectral_constraints.py
agnpy/data/dt_seds/NGC1068_rieke_low_1975.txt
agnpy/data/dt_seds/pier_krolik_1992.txt
agnpy/data/ebl_models/ebl_dominguez11.fits.gz
agnpy/data/ebl_models/ebl_finke10.fits.gz
agnpy/data/ebl_models/ebl_franceschini08.fits.gz
agnpy/data/ebl_models/ebl_saldana-lopez21.fits.gz
agnpy/data/mwl_seds/Mrk421_2011.ecsv
agnpy/data/mwl_seds/PKS1510-089_2015b.ecsv
agnpy/data/reference_seds/dermer_menon_2009/figure_7_4/ssc_gamma_max_1e5.txt
agnpy/data/reference_seds/dermer_menon_2009/figure_7_4/ssc_gamma_max_1e7.txt
agnpy/data/reference_seds/dermer_menon_2009/figure_7_4/synchrotron_gamma_max_1e5.txt
agnpy/data/reference_seds/dermer_menon_2009/figure_7_4/synchrotron_gamma_max_1e7.txt
agnpy/data/reference_seds/finke_2016/figure_10/ec_blr_r_1e16.txt
agnpy/data/reference_seds/finke_2016/figure_10/ec_blr_r_1e17.txt
agnpy/data/reference_seds/finke_2016/figure_10/ec_blr_r_1e18.txt
agnpy/data/reference_seds/finke_2016/figure_10/ec_blr_r_1e19.txt
agnpy/data/reference_seds/finke_2016/figure_11/ec_dt_r_1e18.txt
agnpy/data/reference_seds/finke_2016/figure_11/ec_dt_r_1e19.txt
agnpy/data/reference_seds/finke_2016/figure_11/ec_dt_r_1e20.txt
agnpy/data/reference_seds/finke_2016/figure_11/ec_dt_r_1e21.txt
agnpy/data/reference_seds/finke_2016/figure_8/ec_disk_r_1e17.txt
agnpy/data/reference_seds/finke_2016/figure_8/ec_disk_r_1e18.txt
agnpy/data/reference_seds/finke_2016/figure_8/ec_disk_r_1e19.txt
agnpy/data/reference_seds/jetset/data/ec_cmb_bpwl_jetset_1.1.2.txt
agnpy/data/reference_seds/jetset/data/ssc_pwl_jetset_1.1.2.txt
agnpy/data/reference_seds/jetset/data/synch_pwl_jetset_1.1.2.txt
agnpy/data/reference_seds/jetset/data/synch_ssa_bpwl_jetset_1.1.2.txt
agnpy/data/reference_seds/jetset/data/synch_ssa_lp_jetset_1.1.2.txt
agnpy-0.4.0.dist-info/LICENSE
agnpy-0.4.0.dist-info/METADATA
agnpy-0.4.0.dist-info/WHEEL
agnpy-0.4.0.dist-info/top_level.txt
agnpy-0.4.0.dist-info/RECORD
