Metadata-Version: 2.1
Name: agnpy
Version: 0.4.0
Summary: Modelling jetted Active Galactic Nuclei radiative processes with python
Home-page: https://github.com/cosimoNigro/agnpy
Author: Cosimo Nigro
Author-email: cosimonigro2@gmail.com.com
License: UNKNOWN
Platform: UNKNOWN
Classifier: Programming Language :: Python :: 3
Classifier: Intended Audience :: Science/Research
Classifier: License :: OSI Approved :: BSD License
Classifier: Operating System :: OS Independent
Requires-Python: >=3.8
Requires-Dist: astropy (>=4.0)
Requires-Dist: numpy (>=1.17)
Requires-Dist: scipy (>=1.2)
Requires-Dist: matplotlib
